{"cameraMode":{"drawMode":0,"name":"Shaded","section":"Shading Mode"},"sceneLighting":false,"audioPlay":false,"sceneViewState":{"m_AlwaysRefresh":false,"showFog":true,"showSkybox":false,"showFlares":true,"showImageEffects":true,"showParticleSystems":true,"showVisualEffectGraphs":true,"m_FxEnabled":true},"in2DMode":false,"pivot":{"x":0.940000057220459,"y":-0.0006335973739624023,"z":-2.0136606693267824},"rotation":{"x":-0.10879320651292801,"y":0.48230740427970889,"z":-0.06050841137766838,"w":-0.8671338558197022},"size":2.9295830726623537,"orthographic":false}